{
    "key": "group_620f439b65a9d",
    "title": "Thema opties",
    "fields": [
        {
            "key": "field_620f43a8f0de1",
            "label": "Algemeen",
            "name": "",
            "aria-label": "",
            "type": "tab",
            "instructions": "",
            "required": 0,
            "conditional_logic": 0,
            "wrapper": {
                "width": "",
                "class": "",
                "id": ""
            },
            "placement": "top",
            "endpoint": 0
        },
        {
            "key": "field_6304ea8fb44a4",
            "label": "Logo",
            "name": "logo",
            "aria-label": "",
            "type": "image",
            "instructions": "Gebruik een SVG (of anders PNG van max 230 pixels breed)",
            "required": 0,
            "conditional_logic": 0,
            "wrapper": {
                "width": "50",
                "class": "",
                "id": ""
            },
            "return_format": "id",
            "library": "all",
            "min_width": "",
            "min_height": "",
            "min_size": "",
            "max_width": "",
            "max_height": "",
            "max_size": "",
            "mime_types": "png, svg",
            "preview_size": "medium"
        },
        {
            "key": "field_63cba3ec3d26c",
            "label": "Footer logo",
            "name": "footer_logo",
            "aria-label": "",
            "type": "image",
            "instructions": "Gebruik een SVG (of anders PNG van max 230 pixels breed)",
            "required": 0,
            "conditional_logic": 0,
            "wrapper": {
                "width": "50",
                "class": "",
                "id": ""
            },
            "return_format": "id",
            "library": "all",
            "min_width": "",
            "min_height": "",
            "min_size": "",
            "max_width": "",
            "max_height": "",
            "max_size": "",
            "mime_types": "png, svg",
            "preview_size": "medium"
        },
        {
            "key": "field_63429987ea23d",
            "label": "E-mailadres",
            "name": "email",
            "aria-label": "",
            "type": "link",
            "instructions": "",
            "required": 0,
            "conditional_logic": 0,
            "wrapper": {
                "width": "50",
                "class": "",
                "id": ""
            },
            "return_format": "array"
        },
        {
            "key": "field_6342999aea23e",
            "label": "Telefoonnummer",
            "name": "phone",
            "aria-label": "",
            "type": "link",
            "instructions": "",
            "required": 0,
            "conditional_logic": 0,
            "wrapper": {
                "width": "50",
                "class": "",
                "id": ""
            },
            "return_format": "array"
        },
        {
            "key": "field_634299a4ea23f",
            "label": "Adres",
            "name": "adress",
            "aria-label": "",
            "type": "textarea",
            "instructions": "",
            "required": 0,
            "conditional_logic": 0,
            "wrapper": {
                "width": "70",
                "class": "",
                "id": ""
            },
            "default_value": "",
            "maxlength": "",
            "rows": 3,
            "placeholder": "",
            "new_lines": "br"
        },
        {
            "key": "field_63cab0bb4610a",
            "label": "Footer",
            "name": "",
            "aria-label": "",
            "type": "tab",
            "instructions": "",
            "required": 0,
            "conditional_logic": 0,
            "wrapper": {
                "width": "",
                "class": "",
                "id": ""
            },
            "placement": "top",
            "endpoint": 0
        },
        {
            "key": "field_63cab0c34610b",
            "label": "Certificeringen",
            "name": "footer_certifications",
            "aria-label": "",
            "type": "repeater",
            "instructions": "",
            "required": 0,
            "conditional_logic": 0,
            "wrapper": {
                "width": "",
                "class": "",
                "id": ""
            },
            "layout": "table",
            "pagination": 0,
            "min": 0,
            "max": 0,
            "collapsed": "",
            "button_label": "Nieuwe regel",
            "rows_per_page": 20,
            "sub_fields": [
                {
                    "key": "field_63cab0df4610c",
                    "label": "Certificering",
                    "name": "footer_certification",
                    "aria-label": "",
                    "type": "image",
                    "instructions": "Upload een nieuwe afbeelding, pak er niet een uit de mediabibliotheek. De nieuwe afbeelding wordt automatisch naar het juiste formaat geconverteerd.",
                    "required": 0,
                    "conditional_logic": 0,
                    "wrapper": {
                        "width": "",
                        "class": "",
                        "id": ""
                    },
                    "return_format": "id",
                    "library": "uploadedTo",
                    "min_width": "",
                    "min_height": "",
                    "min_size": "",
                    "max_width": "",
                    "max_height": "",
                    "max_size": "",
                    "mime_types": "",
                    "preview_size": "medium",
                    "parent_repeater": "field_63cab0c34610b"
                }
            ]
        },
        {
            "key": "field_62110c4c43d73",
            "label": "404 pagina",
            "name": "",
            "aria-label": "",
            "type": "tab",
            "instructions": "",
            "required": 0,
            "conditional_logic": 0,
            "wrapper": {
                "width": "",
                "class": "",
                "id": ""
            },
            "placement": "top",
            "endpoint": 0
        },
        {
            "key": "field_62110c6243d74",
            "label": "Titel",
            "name": "error_title",
            "aria-label": "",
            "type": "text",
            "instructions": "",
            "required": 0,
            "conditional_logic": 0,
            "wrapper": {
                "width": "",
                "class": "",
                "id": ""
            },
            "default_value": "",
            "placeholder": "",
            "prepend": "",
            "append": "",
            "maxlength": ""
        },
        {
            "key": "field_62110c6543d75",
            "label": "Content",
            "name": "error_content",
            "aria-label": "",
            "type": "wysiwyg",
            "instructions": "",
            "required": 0,
            "conditional_logic": 0,
            "wrapper": {
                "width": "",
                "class": "",
                "id": ""
            },
            "default_value": "",
            "tabs": "all",
            "toolbar": "full",
            "media_upload": 1,
            "delay": 1
        },
        {
            "key": "field_62305ec82aadf",
            "label": "Footer",
            "name": "",
            "aria-label": "",
            "type": "tab",
            "instructions": "",
            "required": 0,
            "conditional_logic": 0,
            "wrapper": {
                "width": "",
                "class": "",
                "id": ""
            },
            "placement": "top",
            "endpoint": 0
        },
        {
            "key": "field_634420c33d241",
            "label": "Socials",
            "name": "socials",
            "aria-label": "",
            "type": "repeater",
            "instructions": "We hebben <a href=\"https:\/\/www.flaticon.com\/packs\/social-logo-2?word=social\" target=\"_blank\">deze iconen<\/a> gebruikt voor de socials.",
            "required": 0,
            "conditional_logic": 0,
            "wrapper": {
                "width": "",
                "class": "",
                "id": ""
            },
            "layout": "table",
            "pagination": 0,
            "min": 0,
            "max": 0,
            "collapsed": "",
            "button_label": "Add Row",
            "rows_per_page": 20,
            "sub_fields": [
                {
                    "key": "field_634420d63d242",
                    "label": "Link",
                    "name": "social_link",
                    "aria-label": "",
                    "type": "link",
                    "instructions": "",
                    "required": 0,
                    "conditional_logic": 0,
                    "wrapper": {
                        "width": "",
                        "class": "",
                        "id": ""
                    },
                    "return_format": "array",
                    "parent_repeater": "field_634420c33d241"
                },
                {
                    "key": "field_634420ed3d243",
                    "label": "Icoon",
                    "name": "social_icon",
                    "aria-label": "",
                    "type": "image",
                    "instructions": "",
                    "required": 0,
                    "conditional_logic": 0,
                    "wrapper": {
                        "width": "",
                        "class": "",
                        "id": ""
                    },
                    "return_format": "id",
                    "library": "all",
                    "min_width": "",
                    "min_height": "",
                    "min_size": "",
                    "max_width": "",
                    "max_height": "",
                    "max_size": "",
                    "mime_types": "",
                    "preview_size": "medium",
                    "parent_repeater": "field_634420c33d241"
                }
            ]
        }
    ],
    "location": [
        [
            {
                "param": "options_page",
                "operator": "==",
                "value": "options-theme-general"
            }
        ]
    ],
    "menu_order": 0,
    "position": "normal",
    "style": "default",
    "label_placement": "top",
    "instruction_placement": "label",
    "hide_on_screen": "",
    "active": true,
    "description": "",
    "show_in_rest": 0,
    "modified": 1674290181
}